llm_analysis_assistant/__init__.py
llm_analysis_assistant/__main__.py
llm_analysis_assistant/server.py
llm_analysis_assistant/config/.gitignore
llm_analysis_assistant/config/first_open
llm_analysis_assistant/config/num
llm_analysis_assistant/pages/execGET.py
llm_analysis_assistant/pages/execPost.py
llm_analysis_assistant/pages/myMCP.py
llm_analysis_assistant/pages/mySSE.py
llm_analysis_assistant/pages/myStdio.py
llm_analysis_assistant/pages/html/imgs/favicon.ico
llm_analysis_assistant/pages/html/js/index.js
llm_analysis_assistant/pages/html/js/logs_scroll_show.js
llm_analysis_assistant/pages/html/js/mcp.js
llm_analysis_assistant/utils/environ_utils.py
llm_analysis_assistant/utils/http_clientx.py
llm_analysis_assistant/utils/js_utils.py
llm_analysis_assistant/utils/logs_utils.py
llm_analysis_assistant/utils/mock_utils.py
llm_analysis_assistant-0.3.1.dist-info/METADATA
llm_analysis_assistant-0.3.1.dist-info/WHEEL
llm_analysis_assistant-0.3.1.dist-info/entry_points.txt
llm_analysis_assistant-0.3.1.dist-info/licenses/LICENSE
llm_analysis_assistant-0.3.1.dist-info/RECORD
