Metadata-Version: 2.4
Name: llm_analysis_assistant
Version: 0.3.1
Summary: An LLM analysis assistant to help you understand and implement PMF
Project-URL: Repository, https://github.com/xuzexin-hz/llm-analysis-assistant.git
Project-URL: Home-page, https://xuzexin-hz.github.io/pmf-docs/
Author-email: "xuzexin,hz" <1768527366@qq.com>
Maintainer-email: "xuzexin,hz" <1768527366@qq.com>
License: Apache-2.0
License-File: LICENSE
Keywords: analysis,asgi,assistant,llm,mcp,sse,stdio,streamable-http,uvicorn,websocket
Classifier: Development Status :: 4 - Beta
Classifier: Environment :: Web Environment
Classifier: Framework :: AsyncIO
Classifier: Intended Audience :: Developers
Classifier: Intended Audience :: Information Technology
Classifier: License :: OSI Approved :: Apache Software License
Classifier: Natural Language :: Chinese (Simplified)
Classifier: Natural Language :: English
Classifier: Programming Language :: JavaScript
Classifier: Programming Language :: Python :: 3
Classifier: Topic :: Internet
Classifier: Topic :: Internet :: Log Analysis
Classifier: Topic :: Utilities
Requires-Python: >=3.10
Requires-Dist: uvicorn[standard]>=0.34.3
